Workbook

Sheet Dashboard
A1: Professional Inventory Management Dashboard
A3: KPI | B3: Value | D3: Category | E3: Stock Value | G3: Stock Status | H3: Count
A4: Total Products | B4: =COUNTA('Inventory Tracker'!A2:A25) | D4: Electronics | E4: =SUMIF('Inventory Tracker'!C2:C25,D4,'Inventory Tracker'!H2:H25) | G4: In Stock | H4: =COUNTIF('Inventory Tracker'!I2:I25,"In Stock")
A5: Total Stock Units | B5: =SUM('Inventory Tracker'!E2:E25) | D5: Stationery | E5: =SUMIF('Inventory Tracker'!C2:C25,D5,'Inventory Tracker'!H2:H25) | G5: Reorder | H5: =COUNTIF('Inventory Tracker'!I2:I25,"Reorder")
A6: Total Inventory Value | B6: =SUM('Inventory Tracker'!H2:H25) | D6: Furniture | E6: =SUMIF('Inventory Tracker'!C2:C25,D6,'Inventory Tracker'!H2:H25)
A7: Items to Reorder | B7: =COUNTIF('Inventory Tracker'!I2:I25,"Reorder") | D7: Office Supplies | E7: =SUMIF('Inventory Tracker'!C2:C25,D7,'Inventory Tracker'!H2:H25)
A8: Total Transaction Value | B8: =SUM('Purchase and Sales'!G2:G13)

Sheet Inventory Tracker
A1: Item ID | B1: Product Name | C1: Category | D1: Supplier | E1: Stock Qty | F1: Reorder Level | G1: Unit Cost | H1: Stock Value | I1: Stock Status
A2: ITM001 | B2: Wireless Mouse | C2: Electronics | D2: TechSource | E2: 35 | F2: 10 | G2: 799 | H2: =E2*G2 | I2: =IF(E2<=F2,"Reorder","In Stock")
A3: ITM002 | B3: Keyboard | C3: Electronics | D3: TechSource | E3: 8 | F3: 10 | G3: 1499 | H3: =E3*G3 | I3: =IF(E3<=F3,"Reorder","In Stock")
A4: ITM003 | B4: Notebook A4 | C4: Stationery | D4: PaperWorld | E4: 120 | F4: 30 | G4: 120 | H4: =E4*G4 | I4: =IF(E4<=F4,"Reorder","In Stock")
A5: ITM004 | B5: Blue Pen Pack | C5: Stationery | D5: WriteWell | E5: 18 | F5: 25 | G5: 250 | H5: =E5*G5 | I5: =IF(E5<=F5,"Reorder","In Stock")
A6: ITM005 | B6: Office Chair | C6: Furniture | D6: ComfortWorks | E6: 12 | F6: 5 | G6: 6499 | H6: =E6*G6 | I6: =IF(E6<=F6,"Reorder","In Stock")
A7: ITM006 | B7: Laptop Stand | C7: Electronics | D7: DeskTech | E7: 6 | F7: 8 | G7: 1299 | H7: =E7*G7 | I7: =IF(E7<=F7,"Reorder","In Stock")
A8: ITM007 | B8: File Folder | C8: Stationery | D8: PaperWorld | E8: 75 | F8: 20 | G8: 80 | H8: =E8*G8 | I8: =IF(E8<=F8,"Reorder","In Stock")
A9: ITM008 | B9: Desk Lamp | C9: Furniture | D9: BrightHome | E9: 20 | F9: 7 | G9: 899 | H9: =E9*G9 | I9: =IF(E9<=F9,"Reorder","In Stock")
A10: ITM009 | B10: USB Drive 64GB | C10: Electronics | D10: TechSource | E10: 42 | F10: 15 | G10: 599 | H10: =E10*G10 | I10: =IF(E10<=F10,"Reorder","In Stock")
A11: ITM010 | B11: Study Table | C11: Furniture | D11: ComfortWorks | E11: 4 | F11: 5 | G11: 7499 | H11: =E11*G11 | I11: =IF(E11<=F11,"Reorder","In Stock")
A12: ITM011 | B12: Calculator | C12: Stationery | D12: WriteWell | E12: 28 | F12: 10 | G12: 650 | H12: =E12*G12 | I12: =IF(E12<=F12,"Reorder","In Stock")
A13: ITM012 | B13: Webcam | C13: Electronics | D13: DeskTech | E13: 9 | F13: 8 | G13: 2199 | H13: =E13*G13 | I13: =IF(E13<=F13,"Reorder","In Stock")
... A25: ITM024 | B25: Sticky Notes | C25: Stationery | D25: PaperWorld | E25: 65 | F25: 25 | G25: 90 | H25: =E25*G25 | I25: =IF(E25<=F25,"Reorder","In Stock")

Sheet Project Guide
A1: Project Title | B1: Professional Excel Inventory Management & Stock Tracking Portfolio
A2: Overview | B2: A multi-sheet Excel portfolio project for managing inventory, suppliers, purchases, sales, stock value, and reorder status.
A3: Sheets Included | B3: Dashboard; Inventory Tracker; Purchase and Sales; Suppliers; Project Guide.
A4: Excel Skills | B4: Data entry, cleaning, formatting, formulas, IF, COUNTIF, SUMIF, filtering, conditional formatting, dashboards, and charts.
A5: Portfolio Description | B5: Built a professional Excel inventory management workbook with 24 products, supplier records, purchase and sales transactions, automated stock-value calculations, low-stock alerts, KPI reporting, and visual dashboards.

Sheet Purchase and Sales
A1: Transaction ID | B1: Date | C1: Product Name | D1: Type | E1: Quantity | F1: Unit Price | G1: Total Amount | H1: Payment Status
A2: TXN001 | B2: 46174 | C2: Wireless Mouse | D2: Purchase | E2: 20 | F2: 650 | G2: =E2*F2 | H2: Paid
A3: TXN002 | B3: 46176 | C3: Keyboard | D3: Sale | E3: 5 | F3: 1499 | G3: =E3*F3 | H3: Paid
A4: TXN003 | B4: 46178 | C4: Notebook A4 | D4: Purchase | E4: 100 | F4: 90 | G4: =E4*F4 | H4: Paid
A5: TXN004 | B5: 46181 | C5: Office Chair | D5: Sale | E5: 3 | F5: 6499 | G5: =E5*F5 | H5: Paid
A6: TXN005 | B6: 46183 | C6: Laptop Stand | D6: Sale | E6: 4 | F6: 1299 | G6: =E6*F6 | H6: Pending
A7: TXN006 | B7: 46185 | C7: USB Drive 64GB | D7: Purchase | E7: 30 | F7: 450 | G7: =E7*F7 | H7: Paid
A8: TXN007 | B8: 46188 | C8: Study Table | D8: Sale | E8: 2 | F8: 7499 | G8: =E8*F8 | H8: Paid
A9: TXN008 | B9: 46191 | C9: Webcam | D9: Sale | E9: 3 | F9: 2199 | G9: =E9*F9 | H9: Paid
A10: TXN009 | B10: 46193 | C10: Monitor 24 inch | D10: Purchase | E10: 10 | F10: 9500 | G10: =E10*F10 | H10: Paid
A11: TXN010 | B11: 46195 | C11: Headset | D11: Sale | E11: 6 | F11: 1899 | G11: =E11*F11 | H11: Pending
A12: TXN011 | B12: 46198 | C12: HDMI Cable | D12: Sale | E12: 12 | F12: 399 | G12: =E12*F12 | H12: Paid
A13: TXN012 | B13: 46201 | C13: Sticky Notes | D13: Purchase | E13: 50 | F13: 65 | G13: =E13*F13 | H13: Paid

Sheet Suppliers
A1: Supplier ID | B1: Supplier Name | C1: Category Supplied | D1: City | E1: Contact Email | F1: Rating
A2: SUP001 | B2: TechSource | C2: Electronics | D2: Bengaluru | E2: sales@techsource.example | F2: 4.7
A3: SUP002 | B3: PaperWorld | C3: Stationery | D3: Mumbai | E3: orders@paperworld.example | F3: 4.5
A4: SUP003 | B4: WriteWell | C4: Stationery | D4: Delhi | E4: support@writewell.example | F4: 4.3
A5: SUP004 | B5: ComfortWorks | C5: Furniture | D5: Chennai | E5: sales@comfortworks.example | F5: 4.8
A6: SUP005 | B6: DeskTech | C6: Electronics | D6: Hyderabad | E6: orders@desktech.example | F6: 4.6
A7: SUP006 | B7: BrightHome | C7: Furniture | D7: Pune | E7: sales@brighthome.example | F7: 4.2
A8: SUP007 | B8: OfficeMart | C8: Office Supplies | D8: Bengaluru | E8: orders@officemart.example | F8: 4.4
A9: SUP008 | B9: VisionTech | C9: Electronics | D9: Delhi | E9: sales@visiontech.example | F9: 4.6
